{
  "frames": {
    "7": {
      "frame": {
        "x": 0,
        "y": 0,
        "w": 80,
        "h": 80
      },
      "sourceSize": {
        "w": 80,
        "h": 80
      },
      "spriteSourceSize": {
        "x": 0,
        "y": 0,
        "w": 80,
        "h": 80
      }
    },
    "10": {
      "frame": {
        "x": 480,
        "y": 0,
        "w": 80,
        "h": 80
      },
      "sourceSize": {
        "w": 80,
        "h": 80
      },
      "spriteSourceSize": {
        "x": 0,
        "y": 0,
        "w": 80,
        "h": 80
      }
    },
    "BAR": {
      "frame": {
        "x": 80,
        "y": 0,
        "w": 80,
        "h": 80
      },
      "sourceSize": {
        "w": 80,
        "h": 80
      },
      "spriteSourceSize": {
        "x": 0,
        "y": 0,
        "w": 80,
        "h": 80
      }
    },
    "A": {
      "frame": {
        "x": 160,
        "y": 0,
        "w": 80,
        "h": 80
      },
      "sourceSize": {
        "w": 80,
        "h": 80
      },
      "spriteSourceSize": {
        "x": 0,
        "y": 0,
        "w": 80,
        "h": 80
      }
    },
    "K": {
      "frame": {
        "x": 240,
        "y": 0,
        "w": 80,
        "h": 80
      },
      "sourceSize": {
        "w": 80,
        "h": 80
      },
      "spriteSourceSize": {
        "x": 0,
        "y": 0,
        "w": 80,
        "h": 80
      }
    },
    "Q": {
      "frame": {
        "x": 320,
        "y": 0,
        "w": 80,
        "h": 80
      },
      "sourceSize": {
        "w": 80,
        "h": 80
      },
      "spriteSourceSize": {
        "x": 0,
        "y": 0,
        "w": 80,
        "h": 80
      }
    },
    "J": {
      "frame": {
        "x": 400,
        "y": 0,
        "w": 80,
        "h": 80
      },
      "sourceSize": {
        "w": 80,
        "h": 80
      },
      "spriteSourceSize": {
        "x": 0,
        "y": 0,
        "w": 80,
        "h": 80
      }
    }
  },
  "meta": {
    "image": "symbols.png",
    "format": "RGBA8888",
    "size": {
      "w": 560,
      "h": 80
    },
    "scale": 1
  }
}